ml_qol/__init__.py
ml_qol/ensemble.py
ml_qol/feature_engineer.py
ml_qol/handle_data.py
ml_qol/model.py
ml_qol/types.py
ml_qol-0.1.7.dist-info/licenses/LICENSE
ml_qol-0.1.7.dist-info/METADATA
ml_qol-0.1.7.dist-info/WHEEL
ml_qol-0.1.7.dist-info/top_level.txt
ml_qol-0.1.7.dist-info/RECORD
