Metadata-Version: 2.4
Name: ml-qol
Version: 0.1.7
Summary: An ML toolkit package that provides quality-of-life features
Author-email: Mashrur Sakif Souherdo <mashrursakifsouehrdo@gmail.com>
License: MIT License
Requires-Python: >=3.10
License-File: LICENSE
Requires-Dist: pandas
Requires-Dist: numpy
Requires-Dist: scikit-learn
Requires-Dist: catboost
Requires-Dist: lightgbm
Requires-Dist: xgboost
Requires-Dist: matplotlib
Requires-Dist: seaborn
Dynamic: license-file
